aioweb3/__init__.py
aioweb3/async_eth.py
aioweb3/async_web3.py
aioweb3/contract.py
aioweb3/exceptions.py
aioweb3/manager.py
aioweb3/middleware.py
aioweb3/provider.py
aioweb3-0.1.0.dist-info/LICENSE
aioweb3-0.1.0.dist-info/WHEEL
aioweb3-0.1.0.dist-info/METADATA
aioweb3-0.1.0.dist-info/RECORD
