Metadata-Version: 2.1
Name: aioweb3
Version: 0.1.0
Summary: asyncio web3 provider
Author: Omar Bohsali
Author-email: omar.bohsali@gmail.com
Requires-Python: >=3.9,<4.0
Classifier: Programming Language :: Python :: 3
Classifier: Programming Language :: Python :: 3.9
Requires-Dist: web3 (==5.24.0)
